pylemetry/__init__.py
pylemetry/py.typed
pylemetry/registry.py
pylemetry/decorators/__init__.py
pylemetry/decorators/count.py
pylemetry/decorators/time.py
pylemetry/meters/__init__.py
pylemetry/meters/counter.py
pylemetry/meters/gauge.py
pylemetry/meters/meter.py
pylemetry/meters/timer.py
pylemetry/reporting/__init__.py
pylemetry/reporting/logging.py
pylemetry/reporting/reporter.py
pylemetry/reporting/reporting_type.py
pylemetry/utils/__init__.py
pylemetry/utils/timer_units.py
pylemetry-1.2.0.dist-info/METADATA
pylemetry-1.2.0.dist-info/WHEEL
pylemetry-1.2.0.dist-info/licenses/LICENSE
pylemetry-1.2.0.dist-info/RECORD
