Metadata-Version: 2.4
Name: pylemetry
Version: 1.2.0
Summary: A Python metrics library
Project-URL: Homepage, https://pypi.org/project/pylemetry/
Project-URL: Repository, https://github.com/amurphy4/pylemetry
Project-URL: Issues, https://github.com/amurphy4/pylemetry/issues
Author-email: Alex Murphy <alex@weaverslodge.co.uk>
License-Expression: Apache-2.0
License-File: LICENSE
Classifier: Development Status :: 5 - Production/Stable
Classifier: Intended Audience :: Developers
Classifier: License :: OSI Approved :: Apache Software License
Classifier: Programming Language :: Python :: 3
Classifier: Programming Language :: Python :: 3.10
Classifier: Programming Language :: Python :: 3.11
Classifier: Programming Language :: Python :: 3.12
Classifier: Programming Language :: Python :: 3.13
Classifier: Programming Language :: Python :: 3.14
Requires-Python: >=3.10
Requires-Dist: typing-extensions>=4.15.0
